README.md
setup.py
pyuc/__init__.py
pyuc/__main__.py
pyuc/py_api_b.py
pyuc.egg-info/PKG-INFO
pyuc.egg-info/SOURCES.txt
pyuc.egg-info/dependency_links.txt
pyuc.egg-info/top_level.txt
pyuc/py_app/__init__.py
pyuc/py_app/appU.py
pyuc/py_app/ui2pyU.py
pyuc/py_app/windowU.py
pyuc/py_crawl/__init__.py
pyuc/py_crawl/__main__.py
pyuc/py_crawl/chromeU.py
pyuc/py_crawl/httpU.py
pyuc/py_crawl/recordU.py
pyuc/py_crawl/scrapyCommandDemo.py
pyuc/py_crawl/scrapyCommandU.py
pyuc/py_crawl/scrapyCrawlDemo.py
pyuc/py_crawl/scrapyItemU.py
pyuc/py_crawl/scrapyMiddleware.py
pyuc/py_crawl/scrapyPipline.py
pyuc/py_crawl/scrapyRunU.py
pyuc/py_crawl/scrapySaveItem.py
pyuc/py_crawl/scrapySettings.py
pyuc/py_crawl/scrapySpiderDemo.py
pyuc/py_crawl/scrapySpiderU.py
pyuc/py_crawl/scrapyU.py
pyuc/py_crawl/webU.py
pyuc/py_db/__init__.py
pyuc/py_db/mongoDBU.py
pyuc/py_db/mysqlDBU.py
pyuc/py_db/mysqlU.py
pyuc/py_db/redisDBU.py
pyuc/py_file/__init__.py
pyuc/py_file/fileQueueU.py
pyuc/py_file/fileU.py
pyuc/py_file/videoU.py
pyuc/py_memu/__init__.py
pyuc/py_memu/__main__.py
pyuc/py_memu/config.py
pyuc/py_memu/emDemoC.py
pyuc/py_memu/emDemoCM.py
pyuc/py_memu/emDemoOption.py
pyuc/py_memu/memuCMU.py
pyuc/py_memu/memuCU.py
pyuc/py_memu/optionBU.py
pyuc/py_mix/__init__.py
pyuc/py_mix/algorithmU.py
pyuc/py_mix/asyncU.py
pyuc/py_mix/cmdU.py
pyuc/py_mix/ctrlCU.py
pyuc/py_mix/datetimeU.py
pyuc/py_mix/emailU.py
pyuc/py_mix/envU.py
pyuc/py_mix/htmlU.py
pyuc/py_mix/jsU.py
pyuc/py_mix/jsonU.py
pyuc/py_mix/mathU.py
pyuc/py_mix/moduleU.py
pyuc/py_mix/netU.py
pyuc/py_mix/objU.py
pyuc/py_mix/sortU.py
pyuc/py_mix/speechBaiduU.py
pyuc/py_mix/speechU.py
pyuc/py_mix/threadU.py
pyuc/py_mix/xmlU.py
pyuc/py_pfm/__init__.py
pyuc/py_pfm/modelU.py
pyuc/py_pfm/pfmU.py
pyuc/py_phone/__init__.py
pyuc/py_phone/__main__.py
pyuc/py_phone/adbU.py
pyuc/py_phone/androidU.py
pyuc/py_phone/phoneAutoU.py
pyuc/py_proxy/__init__.py
pyuc/py_proxy/mitmproxyU.py
pyuc/py_proxy/proxyCrawlerU.py
pyuc/py_proxy/proxyInfoU.py
pyuc/py_proxy/proxyU.py
pyuc/py_proxy/tls_passthrough.py
pyuc/py_recg/__init__.py
pyuc/py_recg/imgU.py
pyuc/py_recg/tesseractU.py
