Metadata-Version: 1.0
Name: pyuc
Version: 0.0.12
Summary: dbtool,timetool,filetool,phonetool,servertool
Home-page: UNKNOWN
Author: Jack
Author-email: m846999958@gmail.com
License: MIT Licence
Keywords: pip,pytools,pyutils,pyuts,pyus,pyuc
Platform: any
